statepattern.py
statepattern-0.1.0.dist-info/DESCRIPTION.rst
statepattern-0.1.0.dist-info/METADATA
statepattern-0.1.0.dist-info/RECORD
statepattern-0.1.0.dist-info/WHEEL
statepattern-0.1.0.dist-info/metadata.json
statepattern-0.1.0.dist-info/top_level.txt
